test/__init__.py
test/test_agents.py
tsdm/__init__.py
tsdm/agents.py
tsdm/games.py
tsdm_benchmark-0.1.0.dist-info/licenses/LICENSE
tsdm_benchmark-0.1.0.dist-info/METADATA
tsdm_benchmark-0.1.0.dist-info/WHEEL
tsdm_benchmark-0.1.0.dist-info/top_level.txt
tsdm_benchmark-0.1.0.dist-info/RECORD
