Metadata-Version: 2.4
Name: tsdm-benchmark
Version: 0.1.0
Summary: A modular library for benchmarking sequential decision-making models in temporal environments.
Author-email: Mathis Jander <mathis.jander@utwente.nl>
License: MIT
Project-URL: Homepage, https://github.com/MSCA-DN-Digital-Finance/tsdm
Classifier: Programming Language :: Python :: 3
Classifier: License :: OSI Approved :: MIT License
Classifier: Operating System :: OS Independent
Classifier: Intended Audience :: Science/Research
Classifier: Topic :: Scientific/Engineering :: Artificial Intelligence
Requires-Python: >=3.8
License-File: LICENSE
Requires-Dist: numpy
Dynamic: license-file
